talkpipe/__init__.py
talkpipe/app/__init__.py
talkpipe/app/chatterlang_generate_entry_points.py
talkpipe/app/chatterlang_reference_browser.py
talkpipe/app/chatterlang_reference_generator.py
talkpipe/app/chatterlang_script.py
talkpipe/app/chatterlang_serve.py
talkpipe/app/chatterlang_workbench.py
talkpipe/app/talkpipe_plugin_manager.py
talkpipe/app/static/.gitignore
talkpipe/app/static/favicon.ico
talkpipe/app/static/unit-docs.html
talkpipe/app/static/unit-docs.txt
talkpipe/chatterlang/__init__.py
talkpipe/chatterlang/compiler.py
talkpipe/chatterlang/parsers.py
talkpipe/chatterlang/registry.py
talkpipe/data/__init__.py
talkpipe/data/email.py
talkpipe/data/extraction.py
talkpipe/data/html.py
talkpipe/data/mongo.py
talkpipe/data/rss.py
talkpipe/data/text/chunking_units.py
talkpipe/data/text/operations.py
talkpipe/llm/__init__.py
talkpipe/llm/chat.py
talkpipe/llm/config.py
talkpipe/llm/embedding.py
talkpipe/llm/embedding_adapters.py
talkpipe/llm/prompt_adapters.py
talkpipe/operations/__init__.py
talkpipe/operations/filtering.py
talkpipe/operations/matrices.py
talkpipe/operations/thread_ops.py
talkpipe/operations/transforms.py
talkpipe/pipe/__init__.py
talkpipe/pipe/basic.py
talkpipe/pipe/core.py
talkpipe/pipe/fork.py
talkpipe/pipe/io.py
talkpipe/pipe/math.py
talkpipe/pipe/metadata.py
talkpipe/pipelines/__init__.py
talkpipe/pipelines/basic_rag.py
talkpipe/pipelines/vector_databases.py
talkpipe/search/abstract.py
talkpipe/search/lancedb.py
talkpipe/search/whoosh.py
talkpipe/util/__init__.py
talkpipe/util/collections.py
talkpipe/util/config.py
talkpipe/util/constants.py
talkpipe/util/data_manipulation.py
talkpipe/util/doc_extraction.py
talkpipe/util/iterators.py
talkpipe/util/os.py
talkpipe/util/plugin_loader.py
talkpipe-0.11.1.dist-info/licenses/LICENSE
talkpipe-0.11.1.dist-info/METADATA
talkpipe-0.11.1.dist-info/WHEEL
talkpipe-0.11.1.dist-info/entry_points.txt
talkpipe-0.11.1.dist-info/top_level.txt
talkpipe-0.11.1.dist-info/RECORD
