Metadata-Version: 2.4
Name: talkpipe
Version: 0.11.1
Summary: Python internal and external DSL for writing generative AI analytics
Author-email: Travis Bauer <tlbauer@sandia.gov>
Maintainer-email: Travis Bauer <tlbauer@sandia.gov>
License-Expression: Apache-2.0
Project-URL: Homepage, https://github.com/sandialabs/talkpipe
Keywords: ai
Classifier: Development Status :: 3 - Alpha
Classifier: Programming Language :: Python :: 3
Classifier: Operating System :: OS Independent
Requires-Python: >=3.11
License-File: LICENSE
Requires-Dist: prompt_toolkit
Requires-Dist: parsy
Requires-Dist: pydantic
Requires-Dist: requests
Requires-Dist: numpy
Requires-Dist: python-docx
Requires-Dist: pandas
Requires-Dist: feedparser
Requires-Dist: readability-lxml
Requires-Dist: lxml
Requires-Dist: lxml_html_clean
Requires-Dist: fastapi[standard]
Requires-Dist: ipywidgets
Requires-Dist: pymongo
Requires-Dist: scikit-learn
Requires-Dist: uvicorn
Requires-Dist: whoosh
Requires-Dist: lancedb
Requires-Dist: deprecated
Requires-Dist: pyyaml
Requires-Dist: greenlet
Requires-Dist: networkx
Requires-Dist: starlette>=0.49.1
Provides-Extra: dev
Requires-Dist: pytest; extra == "dev"
Requires-Dist: pytest-mock; extra == "dev"
Requires-Dist: pytest-cov; extra == "dev"
Requires-Dist: mongomock; extra == "dev"
Provides-Extra: ollama
Requires-Dist: ollama; extra == "ollama"
Provides-Extra: openai
Requires-Dist: openai; extra == "openai"
Provides-Extra: anthropic
Requires-Dist: anthropic; extra == "anthropic"
Provides-Extra: all
Requires-Dist: talkpipe[anthropic,ollama,openai]; extra == "all"
Dynamic: license-file
